mkdocs_psinder-0.4.0.dist-info/DESCRIPTION.rst
mkdocs_psinder-0.4.0.dist-info/METADATA
mkdocs_psinder-0.4.0.dist-info/RECORD
mkdocs_psinder-0.4.0.dist-info/WHEEL
mkdocs_psinder-0.4.0.dist-info/entry_points.txt
mkdocs_psinder-0.4.0.dist-info/metadata.json
mkdocs_psinder-0.4.0.dist-info/top_level.txt
psinder/404.html
psinder/__init__.py
psinder/base.html
psinder/content.html
psinder/disqus.html
psinder/nav-sub.html
psinder/nav.html
psinder/toc.html
psinder/css/base.css
psinder/css/bootstrap-custom.css
psinder/css/bootstrap-custom.min.css
psinder/css/font-awesome-4.0.3.css
psinder/css/highlight.css
psinder/css/highlight.nowrap.css
psinder/css/psinder.css
psinder/fonts/fontawesome-webfont.eot
psinder/fonts/fontawesome-webfont.svg
psinder/fonts/fontawesome-webfont.ttf
psinder/fonts/fontawesome-webfont.woff
psinder/img/favicon.ico
psinder/img/grid1.png
psinder/img/grid10.png
psinder/img/grid11.png
psinder/img/grid12.png
psinder/img/grid13.png
psinder/img/grid14.png
psinder/img/grid15.png
psinder/img/grid16.png
psinder/img/grid17.png
psinder/img/grid18.png
psinder/img/grid19.png
psinder/img/grid2.png
psinder/img/grid20.png
psinder/img/grid3.png
psinder/img/grid4.png
psinder/img/grid5.png
psinder/img/grid6.png
psinder/img/grid7.png
psinder/img/grid8.png
psinder/img/grid9.png
psinder/js/base.js
psinder/js/bootstrap-3.0.3.min.js
psinder/js/highlight.pack.js
psinder/js/jquery-1.10.2.min.js
psinder/js/tags.js
site/__init__.py
