Metadata-Version: 2.0
Name: mkdocs-psinder
Version: 0.4.0
Summary: A clean, responsive PowerShell-inspired theme for static documentation websites that are generated with MkDocs - forked with love from Chris Simpkins Cinder
Home-page: https://github.com/michaeltlombardi/mkdocs-psinder
Author: Michael T Lombardi
Author-email: michael.t.lombardi@outlook.com
License: MIT
Platform: UNKNOWN
